evalgraph/__init__.py
evalgraph/marketscenarios.py
evalgraph/node_example.py
evalgraph/option.py
evalgraph/core/__init__.py
evalgraph/core/graphevaluator.py
evalgraph/core/nodes.py
evalgraph/core/scenariocontext.py
evalgraph/core/scenarios.py
evalgraph-0.1.3.dist-info/METADATA
evalgraph-0.1.3.dist-info/WHEEL
evalgraph-0.1.3.dist-info/top_level.txt
evalgraph-0.1.3.dist-info/RECORD
