Metadata-Version: 2.1
Name: evalgraph
Version: 0.1.3
Summary: Graph based evaluator
Home-page: https://github.com/joelhoro/graph
Author: Joel Horowitz
Author-email: joelhoro@gmail.com
License: UNKNOWN
Platform: UNKNOWN
Classifier: Programming Language :: Python :: 3
Classifier: License :: OSI Approved :: MIT License
Classifier: Operating System :: OS Independent
Requires-Python: >=3.6
Requires-Dist: pandas
Requires-Dist: scipy
